cut_detector/__init__.py
cut_detector/_version.py
cut_detector/_widget.py
cut_detector/napari.yaml
cut_detector/_tests/__init__.py
cut_detector/_tests/test_annotations_upload.py
cut_detector/_tests/test_functions.py
cut_detector/_tests/test_micro_tubules_cut_detection.py
cut_detector/_tests/test_mid_body_detection.py
cut_detector/_tests/test_results_saving.py
cut_detector/_tests/test_segmentation_tracking.py
cut_detector/_tests/test_track_generation.py
cut_detector/_tests/test_whole_process.py
cut_detector/constants/__init__.py
cut_detector/constants/annotations.py
cut_detector/data/__init__.py
cut_detector/data/tools.py
cut_detector/factories/__init__.py
cut_detector/factories/mid_body_detection_factory.py
cut_detector/factories/mitosis_track_generation_factory.py
cut_detector/factories/mt_cut_detection_factory.py
cut_detector/factories/results_saving_factory.py
cut_detector/factories/segmentation_tracking_factory.py
cut_detector/models/__init__.py
cut_detector/models/tools.py
cut_detector/utils/__init__.py
cut_detector/utils/box_dimensions.py
cut_detector/utils/box_dimensions_contour.py
cut_detector/utils/cell_spot.py
cut_detector/utils/cell_track.py
cut_detector/utils/cnn_data_set.py
cut_detector/utils/division.py
cut_detector/utils/hidden_markov_models.py
cut_detector/utils/image_tools.py
cut_detector/utils/metaphase_sequence.py
cut_detector/utils/mid_body_spot.py
cut_detector/utils/mid_body_track.py
cut_detector/utils/mitosis_track.py
cut_detector/utils/parameters.py
cut_detector/utils/spot.py
cut_detector/utils/statistical_tests.py
cut_detector/utils/tools.py
cut_detector/utils/track.py
cut_detector/utils/track_generation.py
cut_detector/utils/mid_body_detection/__init__.py
cut_detector/utils/mid_body_detection/detection.py
cut_detector/utils/mid_body_detection/spatial_laptrack.py
cut_detector/utils/mid_body_detection/tracking.py
cut_detector/utils/mitosis_track_generation/__init__.py
cut_detector/utils/mitosis_track_generation/metaphase_cnn_data_set.py
cut_detector-1.6.5.dist-info/licenses/LICENSE
cut_detector-1.6.5.dist-info/METADATA
cut_detector-1.6.5.dist-info/WHEEL
cut_detector-1.6.5.dist-info/entry_points.txt
cut_detector-1.6.5.dist-info/top_level.txt
cut_detector-1.6.5.dist-info/RECORD
