Metadata-Version: 2.4
Name: cut-detector
Version: 1.6.5
Summary: Automatic Cut Detector
Home-page: https://github.com/15bonte/cut-detector
Author: Thomas Bonte
Author-email: thomas.bonte@mines-paristech.fr
License: BSD-3-Clause
Project-URL: Bug Tracker, https://github.com/15bonte/cut-detector/issues
Project-URL: Documentation, https://github.com/15bonte/cut-detector#README.md
Project-URL: Source Code, https://github.com/15bonte/cut-detector
Project-URL: User Support, https://github.com/15bonte/cut-detector/issues
Classifier: Development Status :: 2 - Pre-Alpha
Classifier: Framework :: napari
Classifier: Intended Audience :: Developers
Classifier: License :: OSI Approved :: BSD License
Classifier: Operating System :: OS Independent
Classifier: Programming Language :: Python
Classifier: Programming Language :: Python :: 3
Classifier: Programming Language :: Python :: 3 :: Only
Classifier: Programming Language :: Python :: 3.9
Classifier: Programming Language :: Python :: 3.10
Classifier: Topic :: Scientific/Engineering :: Image Processing
Requires-Python: >=3.9
License-File: LICENSE
Requires-Dist: cellpose==3.0.9
Requires-Dist: pyimagej
Requires-Dist: cnn_framework==0.0.16
Requires-Dist: magicgui
Requires-Dist: pydantic==1.10.12
Requires-Dist: xmltodict
Requires-Dist: shapely
Requires-Dist: aicsimageio==4.14.0
Requires-Dist: fsspec==2023.6.0
Requires-Dist: charset-normalizer==3.3.0
Requires-Dist: napari[all]
Requires-Dist: laptrack==0.16.2
Requires-Dist: scikit-learn==1.5.0
Requires-Dist: numba>=0.59.1
Requires-Dist: scipy<=1.14.1
Requires-Dist: tensorflow<=2.18.0
Requires-Dist: munch
Requires-Dist: plotly
Provides-Extra: testing
Requires-Dist: tox; extra == "testing"
Requires-Dist: pytest; extra == "testing"
Requires-Dist: pytest-cov; extra == "testing"
Requires-Dist: pytest-qt; extra == "testing"
Requires-Dist: napari; extra == "testing"
Requires-Dist: pyqt5; extra == "testing"
Dynamic: license-file
